SlideRunner_dataAccess/__init__.py
SlideRunner_dataAccess/annotations.py
SlideRunner_dataAccess/cellvizio.py
SlideRunner_dataAccess/database.py
SlideRunner_dataAccess/dicomimage.py
SlideRunner_dataAccess/nifty.py
SlideRunner_dataAccess/slide.py
SlideRunner_dataAccess-1.0.9.dist-info/LICENSE
SlideRunner_dataAccess-1.0.9.dist-info/METADATA
SlideRunner_dataAccess-1.0.9.dist-info/WHEEL
SlideRunner_dataAccess-1.0.9.dist-info/top_level.txt
SlideRunner_dataAccess-1.0.9.dist-info/RECORD
